rand/__init__.py
rand/_calc.py
rand/_calc_old.py
rand/common/__init__.py
rand/common/int_t.py
rand/common/int_t_gen.py
rand/common/intwise.py
rand/modules/__init__.py
rand/modules/_template.py
rand/modules/aesctr.py
rand/modules/aesdragontamer.py
rand/modules/jenkinssmall.py
rand/modules/lehmer64.py
rand/modules/mersennetwister.py
rand/modules/mitchellmoore.py
rand/modules/pcg32.py
rand/modules/pcg64.py
rand/modules/splitmix64.py
rand/modules/wyhash64.py
rand/modules/xorshift32.py
RandX-0.0.1.post0.dist-info/LICENSE
RandX-0.0.1.post0.dist-info/METADATA
RandX-0.0.1.post0.dist-info/WHEEL
RandX-0.0.1.post0.dist-info/top_level.txt
RandX-0.0.1.post0.dist-info/RECORD
